starlette_middleware/__init__.py
starlette_middleware/middleware.py
starlette_middleware/backend/__init__.py
starlette_middleware/backend/base.py
starlette_middleware/backend/redis.py
starlette_middleware/ext/__init__.py
starlette_middleware/ext/encoding.py
starlette_middleware-0.0.2a1.dist-info/METADATA
starlette_middleware-0.0.2a1.dist-info/WHEEL
starlette_middleware-0.0.2a1.dist-info/licenses/LICENSE.md
starlette_middleware-0.0.2a1.dist-info/RECORD
